README.md
setup.py
django_nosql/__init__.py
django_nosql/admin.py
django_nosql/apps.py
django_nosql/backends.py
django_nosql/models.py
django_nosql/signals.py
django_nosql/tests.py
django_nosql/views.py
django_nosql.egg-info/PKG-INFO
django_nosql.egg-info/SOURCES.txt
django_nosql.egg-info/dependency_links.txt
django_nosql.egg-info/top_level.txt