Metadata-Version: 2.1
Name: django-nosql
Version: 0.0.3
Summary: Stream model updates to nosql backends
Home-page: https://gitlab.com/SchoolOrchestration/django_nosql.git
Author: Christo Crampton
Author-email: christo@appointmentguru.co
License: UNKNOWN
Platform: UNKNOWN
Classifier: Programming Language :: Python :: 3
Classifier: Operating System :: OS Independent
